meme_manager/__init__.py
meme_manager/cli.py
meme_manager/configs.py
meme_manager/create_app.py
meme_manager/models.py
meme_manager/version.py
meme_manager/views.py
meme_manager/frontend/asset-manifest.json
meme_manager/frontend/favicon.ico
meme_manager/frontend/index.html
meme_manager/frontend/logo192.png
meme_manager/frontend/logo512.png
meme_manager/frontend/manifest.json
meme_manager/frontend/precache-manifest.506155c953fdbd21e838d19282ed93ea.js
meme_manager/frontend/precache-manifest.735bce43510fac2c82fd581811365145.js
meme_manager/frontend/robots.txt
meme_manager/frontend/service-worker.js
meme_manager/frontend/static/css/2.1bd2ab2f.chunk.css
meme_manager/frontend/static/css/2.1bd2ab2f.chunk.css.map
meme_manager/frontend/static/css/2.2fbe55bd.chunk.css
meme_manager/frontend/static/css/2.2fbe55bd.chunk.css.map
meme_manager/frontend/static/css/main.a3ac8293.chunk.css
meme_manager/frontend/static/css/main.a3ac8293.chunk.css.map
meme_manager/frontend/static/js/2.42e0e759.chunk.js
meme_manager/frontend/static/js/2.42e0e759.chunk.js.LICENSE.txt
meme_manager/frontend/static/js/2.42e0e759.chunk.js.map
meme_manager/frontend/static/js/2.b35cb96f.chunk.js
meme_manager/frontend/static/js/2.b35cb96f.chunk.js.LICENSE.txt
meme_manager/frontend/static/js/2.b35cb96f.chunk.js.map
meme_manager/frontend/static/js/main.08a309e4.chunk.js
meme_manager/frontend/static/js/main.08a309e4.chunk.js.map
meme_manager/frontend/static/js/main.9e102984.chunk.js
meme_manager/frontend/static/js/main.9e102984.chunk.js.map
meme_manager/frontend/static/js/runtime-main.08295f2d.js
meme_manager/frontend/static/js/runtime-main.08295f2d.js.map
meme_manager-0.3.1.dist-info/LICENSE
meme_manager-0.3.1.dist-info/METADATA
meme_manager-0.3.1.dist-info/WHEEL
meme_manager-0.3.1.dist-info/entry_points.txt
meme_manager-0.3.1.dist-info/top_level.txt
meme_manager-0.3.1.dist-info/RECORD
