Metadata-Version: 2.1
Name: meme-manager
Version: 0.3.1
Summary: A meme manager with web UI
Home-page: https://github.com/valleygtc/meme-manager
Author: gutianci
Author-email: gutianci@qq.com
License: UNKNOWN
Project-URL: Bug Reports, https://github.com/valleygtc/meme-manager/issues
Project-URL: Source, https://github.com/valleygtc/meme-manager/
Keywords: application web
Platform: UNKNOWN
Classifier: Development Status :: 3 - Alpha
Classifier: Environment :: Web Environment
Classifier: Intended Audience :: End Users/Desktop
Classifier: Topic :: Desktop Environment
Classifier: License :: OSI Approved :: GNU General Public License v3 or later (GPLv3+)
Classifier: Programming Language :: Python :: 3.6
Classifier: Programming Language :: Python :: 3.7
Classifier: Programming Language :: Python :: 3.8
Classifier: Operating System :: OS Independent
Requires-Python: >=3.6
Requires-Dist: flask
Requires-Dist: flask-sqlalchemy
Requires-Dist: waitress
